{
  "actualizado": "2026-07-04T13:56:39.524Z",
  "muestras": {
    "zarautz": [
      {
        "t": 1783147427468,
        "i": 0
      },
      {
        "t": 1783147597232,
        "i": 0
      },
      {
        "t": 1783147904080,
        "i": 0
      },
      {
        "t": 1783156170299,
        "i": 0
      },
      {
        "t": 1783162796995,
        "i": 0
      },
      {
        "t": 1783167033476,
        "i": 0
      },
      {
        "t": 1783173399524,
        "i": 0
      }
    ],
    "donostia": [
      {
        "t": 1783147427468,
        "i": 0
      },
      {
        "t": 1783147597232,
        "i": 0
      },
      {
        "t": 1783147904080,
        "i": 0
      },
      {
        "t": 1783156170299,
        "i": 0
      },
      {
        "t": 1783162796995,
        "i": 0
      },
      {
        "t": 1783167033476,
        "i": 0
      },
      {
        "t": 1783173399524,
        "i": 0
      }
    ],
    "irun": [
      {
        "t": 1783147427468,
        "i": 0
      },
      {
        "t": 1783147597232,
        "i": 0
      },
      {
        "t": 1783147904080,
        "i": 0
      },
      {
        "t": 1783156170299,
        "i": 0
      },
      {
        "t": 1783162796995,
        "i": 0
      },
      {
        "t": 1783167033476,
        "i": 0
      },
      {
        "t": 1783173399524,
        "i": 0
      }
    ],
    "eibar": [
      {
        "t": 1783147597232,
        "i": 0
      },
      {
        "t": 1783147904080,
        "i": 0
      },
      {
        "t": 1783156170299,
        "i": 0
      },
      {
        "t": 1783162796995,
        "i": 0
      },
      {
        "t": 1783167033476,
        "i": 0
      },
      {
        "t": 1783173399524,
        "i": 0
      }
    ]
  },
  "ultimosFallos": null
}
